ipam/__init__.py
ipam/client/__init__.py
ipam/client/abstractipam.py
ipam/client/backends/__init__.py
ipam/client/backends/phpipam.py
ipam/client/tests/test_phpipam.py
ipam/client/tests/data/db-no-settings.sql
ipam/client/tests/data/db-old-version.sql
ipam/client/tests/data/db-recent-version.sql
ipam_client-0.6.6.dist-info/AUTHORS
ipam_client-0.6.6.dist-info/LICENSE.txt
ipam_client-0.6.6.dist-info/METADATA
ipam_client-0.6.6.dist-info/WHEEL
ipam_client-0.6.6.dist-info/top_level.txt
ipam_client-0.6.6.dist-info/RECORD
