Metadata-Version: 2.1
Name: ipam-client
Version: 0.6.6
Summary: IPAM abstraction layer library
Home-page: UNKNOWN
Author: Criteo
Author-email: github@criteo.com
License: Apache
Project-URL: Source Code, https://github.com/criteo/ipam-client
Keywords: ipam,phpipam
Platform: UNKNOWN
Classifier: Development Status :: 4 - Beta
Classifier: Intended Audience :: Developers
Classifier: Topic :: Software Development :: Build Tools
Classifier: License :: OSI Approved :: Apache Software License
Classifier: Programming Language :: Python :: 2
Classifier: Programming Language :: Python :: 2.7
Classifier: Programming Language :: Python :: 3
Classifier: Programming Language :: Python :: 3.4
Classifier: Programming Language :: Python :: 3.5
Classifier: Programming Language :: Python :: 3.6
License-File: LICENSE.txt
License-File: AUTHORS
Requires-Dist: ipaddress
Requires-Dist: mysql-connector-python (>=8.0.23)
